cosmofy/__init__.py
cosmofy/__main__.py
cosmofy/args.py
cosmofy/baton.py
cosmofy/bundle.py
cosmofy/fs/__init__.py
cosmofy/fs/__main__.py
cosmofy/fs/add.py
cosmofy/fs/args.py
cosmofy/fs/cat.py
cosmofy/fs/ls.py
cosmofy/fs/rm.py
cosmofy/py.typed
cosmofy/self/__init__.py
cosmofy/self/__main__.py
cosmofy/self/update.py
cosmofy/self/version.py
cosmofy/updater/__init__.py
cosmofy/updater/__main__.py
cosmofy/updater/add.py
cosmofy/updater/check.py
cosmofy/updater/downloader.py
cosmofy/updater/pythonoid.py
cosmofy/updater/receipt.py
cosmofy/updater/remove.py
cosmofy/updater/run.py
cosmofy/zipfile2.py
cosmofy-0.2.1.dist-info/licenses/LICENSE.md
cosmofy-0.2.1.dist-info/WHEEL
cosmofy-0.2.1.dist-info/entry_points.txt
cosmofy-0.2.1.dist-info/METADATA
cosmofy-0.2.1.dist-info/RECORD
