Metadata-Version: 2.4
Name: cosmofy
Version: 0.2.1
Summary: Cosmopolitan Python Bundler
Keywords: cosmopolitan,bundler
Author: Metaist LLC
Author-email: Metaist LLC <metaist@metaist.com>
License-Expression: MIT
License-File: LICENSE.md
Classifier: Development Status :: 4 - Beta
Classifier: Intended Audience :: Developers
Classifier: License :: OSI Approved :: MIT License
Classifier: Natural Language :: English
Classifier: Operating System :: OS Independent
Classifier: Programming Language :: Python
Classifier: Programming Language :: Python :: 3
Classifier: Programming Language :: Python :: 3 :: Only
Classifier: Programming Language :: Python :: 3.10
Classifier: Programming Language :: Python :: 3.11
Classifier: Programming Language :: Python :: 3.12
Classifier: Topic :: Software Development :: Build Tools
Classifier: Typing :: Typed
Requires-Python: >=3.10, <3.13
Project-URL: Changelog, https://github.com/metaist/cosmofy/blob/main/CHANGELOG.md
Project-URL: Documentation, https://metaist.github.io/cosmofy/
Project-URL: Homepage, https://github.com/metaist/cosmofy
Project-URL: Repository, https://github.com/metaist/cosmofy.git
